src/Code/A1_first_win.py
src/Code/A2_loading_win.py
src/Code/A2_photo_win.py
src/Code/A3_export_data_win.py
src/Code/A4_pdf_win.py
src/Code/A5_final_win.py
src/Code/Algo_main_CelebA_vf.py
src/Code/Autoencodeur.py
src/Code/Tuto.py
src/Code/image_celeba.py
src/Code/retrain.py
src/Code/start_software_faces.py
src/Code/train.py
src/Code/docs/Makefile
src/Code/docs/make.bat
src/Code/docs/build/doctrees/A1_first_win.doctree
src/Code/docs/build/doctrees/A2_loading_win.doctree
src/Code/docs/build/doctrees/A2_photo_win.doctree
src/Code/docs/build/doctrees/A3_export_data_win.doctree
src/Code/docs/build/doctrees/A4_pdf_win.doctree
src/Code/docs/build/doctrees/A5_final_win.doctree
src/Code/docs/build/doctrees/Algo_main_CelebA.doctree
src/Code/docs/build/doctrees/Algo_main_CelebA_vf.doctree
src/Code/docs/build/doctrees/Autoencodeur.doctree
src/Code/docs/build/doctrees/Main_test.doctree
src/Code/docs/build/doctrees/Tuto.doctree
src/Code/docs/build/doctrees/environment.pickle
src/Code/docs/build/doctrees/image_celeba.doctree
src/Code/docs/build/doctrees/index.doctree
src/Code/docs/build/doctrees/intro.doctree
src/Code/docs/build/doctrees/modules.doctree
src/Code/docs/build/doctrees/retrain.doctree
src/Code/docs/build/doctrees/train.doctree
src/Code/docs/build/html/.buildinfo
src/Code/docs/build/html/.nojekyll
src/Code/docs/build/html/A1_first_win.html
src/Code/docs/build/html/A2_loading_win.html
src/Code/docs/build/html/A2_photo_win.html
src/Code/docs/build/html/A3_export_data_win.html
src/Code/docs/build/html/A4_pdf_win.html
src/Code/docs/build/html/A5_final_win.html
src/Code/docs/build/html/Algo_main_CelebA.html
src/Code/docs/build/html/Algo_main_CelebA_vf.html
src/Code/docs/build/html/Autoencodeur.html
src/Code/docs/build/html/Main_test.html
src/Code/docs/build/html/Tuto.html
src/Code/docs/build/html/genindex.html
src/Code/docs/build/html/image_celeba.html
src/Code/docs/build/html/index.html
src/Code/docs/build/html/intro.html
src/Code/docs/build/html/modules.html
Code_groupe1_laguilhon-0.0.1.dist-info/LICENSE
Code_groupe1_laguilhon-0.0.1.dist-info/METADATA
Code_groupe1_laguilhon-0.0.1.dist-info/WHEEL
Code_groupe1_laguilhon-0.0.1.dist-info/top_level.txt
Code_groupe1_laguilhon-0.0.1.dist-info/RECORD
